{
  "SPDXID" : "SPDXRef-DOCUMENT",
  "spdxVersion" : "SPDX-2.3",
  "creationInfo" : {
    "comment" : "Converted from CycloneDX spec version 1.4",
    "created" : "2023-11-24T15:17:43Z",
    "creators" : [ "Tool: CycloneDX:cyclonedx-bom-3.11.7", "Tool: CycloneDX:cyclonedx-python-lib-3.1.5", "Tool: CycloneToSpdx-0.1.4" ],
    "licenseListVersion" : "3.22"
  },
  "name" : "From-Cyclone-DX",
  "dataLicense" : "CC0-1.0",
  "annotations" : [ {
    "annotationDate" : "2023-11-24T15:17:46Z",
    "annotationType" : "OTHER",
    "annotator" : "Tool: CycloneToSpdx",
    "comment" : "MISSING_CDX_PROPERTY:extensions={}"
  } ],
  "documentNamespace" : "https://cyclonedx/685cc6b5-abee-4cb3-861e-41ba762c6f5d_1",
  "packages" : [ {
    "SPDXID" : "SPDXRef-10ecb281-5065-4955-9b41-2dbab518a651",
    "annotations" : [ {
      "annotationDate" : "2023-11-24T15:17:46Z",
      "annotationType" : "OTHER",
      "annotator" : "Tool: CycloneToSpdx",
      "comment" : "MISSING_CDX_PROPERTY:componentType=\"LIBRARY\""
    } ],
    "copyrightText" : "NOASSERTION",
    "downloadLocation" : "NOASSERTION",
    "externalRefs" : [ {
      "referenceCategory" : "PACKAGE-MANAGER",
      "referenceLocator" : "pkg:pypi/msgspec@0.18.4",
      "referenceType" : "purl"
    } ],
    "filesAnalyzed" : false,
    "licenseConcluded" : "NOASSERTION",
    "licenseDeclared" : "NOASSERTION",
    "name" : "msgspec",
    "primaryPackagePurpose" : "LIBRARY",
    "versionInfo" : "0.18.4"
  }, {
    "SPDXID" : "SPDXRef-6afef051-bf20-4e7e-99b7-12ce3897f8aa",
    "annotations" : [ {
      "annotationDate" : "2023-11-24T15:17:46Z",
      "annotationType" : "OTHER",
      "annotator" : "Tool: CycloneToSpdx",
      "comment" : "MISSING_CDX_PROPERTY:componentType=\"LIBRARY\""
    } ],
    "copyrightText" : "NOASSERTION",
    "downloadLocation" : "NOASSERTION",
    "externalRefs" : [ {
      "referenceCategory" : "PACKAGE-MANAGER",
      "referenceLocator" : "pkg:pypi/httpx@0.25.2",
      "referenceType" : "purl"
    } ],
    "filesAnalyzed" : false,
    "licenseConcluded" : "NOASSERTION",
    "licenseDeclared" : "NOASSERTION",
    "name" : "httpx",
    "primaryPackagePurpose" : "LIBRARY",
    "versionInfo" : "0.25.2"
  }, {
    "SPDXID" : "SPDXRef-8b48de7e-c5c4-4d3e-907f-85cd193f5991",
    "annotations" : [ {
      "annotationDate" : "2023-11-24T15:17:46Z",
      "annotationType" : "OTHER",
      "annotator" : "Tool: CycloneToSpdx",
      "comment" : "MISSING_CDX_PROPERTY:componentType=\"LIBRARY\""
    } ],
    "copyrightText" : "NOASSERTION",
    "downloadLocation" : "NOASSERTION",
    "externalRefs" : [ {
      "referenceCategory" : "PACKAGE-MANAGER",
      "referenceLocator" : "pkg:pypi/attrs@23.1.0",
      "referenceType" : "purl"
    } ],
    "filesAnalyzed" : false,
    "licenseConcluded" : "NOASSERTION",
    "licenseDeclared" : "NOASSERTION",
    "name" : "attrs",
    "primaryPackagePurpose" : "LIBRARY",
    "versionInfo" : "23.1.0"
  } ],
  "relationships" : [ {
    "spdxElementId" : "SPDXRef-DOCUMENT",
    "relationshipType" : "DESCRIBES",
    "relatedSpdxElement" : "SPDXRef-8b48de7e-c5c4-4d3e-907f-85cd193f5991"
  }, {
    "spdxElementId" : "SPDXRef-DOCUMENT",
    "relationshipType" : "DESCRIBES",
    "relatedSpdxElement" : "SPDXRef-10ecb281-5065-4955-9b41-2dbab518a651"
  }, {
    "spdxElementId" : "SPDXRef-DOCUMENT",
    "relationshipType" : "DESCRIBES",
    "relatedSpdxElement" : "SPDXRef-6afef051-bf20-4e7e-99b7-12ce3897f8aa"
  } ]
}